{
  "id": "header",
  "type": "SharedSlice",
  "name": "Header",
  "description": "Header",
  "variations": [
    {
      "id": "default",
      "name": "Default",
      "docURL": "...",
      "version": "initial",
      "description": "Default",
      "imageUrl": "",
      "primary": {
        "logo": {
          "type": "Image",
          "config": {
            "label": "logo",
            "constraint": {},
            "thumbnails": []
          }
        },
        "name": {
          "type": "StructuredText",
          "config": {
            "label": "name",
            "placeholder": "",
            "allowTargetBlank": true,
            "single": "paragraph,preformatted,heading1,heading2,heading3,heading4,heading5,heading6,strong,em,hyperlink,image,embed,list-item,o-list-item,rtl"
          }
        }
      },
      "items": {
        "button": {
          "type": "Text",
          "config": {
            "label": "button",
            "placeholder": ""
          }
        }
      }
    }
  ]
}